{"stats":{"minecraft:picked_up":{"minecraft:gray_concrete_powder":3},"minecraft:killed_by":{"minecraft:player":1},"minecraft:custom":{"minecraft:time_since_rest":756,"minecraft:play_one_minute":174811,"minecraft:crouch_one_cm":28840,"minecraft:open_shulker_box":7,"minecraft:sprint_one_cm":557958,"minecraft:interact_with_loom":1,"minecraft:damage_taken":5100,"minecraft:deaths":11,"minecraft:walk_one_cm":191362,"minecraft:sneak_time":8377,"minecraft:bell_ring":2,"minecraft:walk_under_water_one_cm":6223,"minecraft:interact_with_anvil":1,"minecraft:jump":4836,"minecraft:damage_dealt":120,"minecraft:interact_with_blast_furnace":1,"minecraft:leave_game":17,"minecraft:walk_on_water_one_cm":12531,"minecraft:time_since_death":736,"minecraft:climb_one_cm":20624,"minecraft:swim_one_cm":43933,"minecraft:fall_one_cm":230517,"minecraft:fly_one_cm":938264}},"DataVersion":2584}