{"stats":{"minecraft:custom":{"minecraft:time_since_rest":6408,"minecraft:play_one_minute":6408,"minecraft:crouch_one_cm":284,"minecraft:sprint_one_cm":20535,"minecraft:damage_taken":167,"minecraft:walk_one_cm":12062,"minecraft:sneak_time":104,"minecraft:walk_under_water_one_cm":2858,"minecraft:drop":11,"minecraft:jump":170,"minecraft:damage_dealt":25,"minecraft:leave_game":1,"minecraft:time_since_death":6408,"minecraft:walk_on_water_one_cm":10000,"minecraft:swim_one_cm":71,"minecraft:fly_one_cm":22781},"minecraft:mined":{"minecraft:grass_block":2},"minecraft:picked_up":{"minecraft:allium":2,"minecraft:peony":2,"minecraft:wheat_seeds":1,"minecraft:red_tulip":1,"minecraft:rose_bush":1,"minecraft:bamboo":9,"minecraft:lily_of_the_valley":1,"minecraft:dirt":4},"minecraft:dropped":{"minecraft:dirt":3,"minecraft:bamboo":9,"minecraft:wheat_seeds":1,"minecraft:red_tulip":1,"minecraft:allium":2,"minecraft:peony":2,"minecraft:rose_bush":1,"minecraft:lily_of_the_valley":1},"minecraft:used":{"minecraft:dirt":1}},"DataVersion":2586}